db_magic/__init__.py
db_magic/magic.py
db_magic/schema_upgrades.py
bp_db_magic-0.2.dist-info/METADATA
bp_db_magic-0.2.dist-info/WHEEL
bp_db_magic-0.2.dist-info/top_level.txt
bp_db_magic-0.2.dist-info/RECORD
